steven/__init__.py
steven/binning.py
steven/sampling.py
steven/seeds.py
steven-0.3.3.dist-info/licenses/LICENSE
steven-0.3.3.dist-info/METADATA
steven-0.3.3.dist-info/WHEEL
steven-0.3.3.dist-info/top_level.txt
steven-0.3.3.dist-info/RECORD
