Metadata-Version: 2.4
Name: steven
Version: 0.3.3
Summary: Sample Things EVENly
Author: Michael Peter Dunne
Classifier: Programming Language :: Python :: 3
Classifier: License :: OSI Approved :: MIT License
Requires-Python: >=3.8
License-File: LICENSE
Requires-Dist: numpy
Requires-Dist: pandas
Requires-Dist: tqdm
Dynamic: license-file
